{
  "project_info": {
    "project_number": "451569691926",
    "project_id": "middleware-5d4b6",
    "storage_bucket": "middleware-5d4b6.appspot.com"
  },
  "client": [
    {
      "client_info": {
        "mobilesdk_app_id": "1:451569691926:android:1043609bb080d94d88f437",
        "android_client_info": {
          "package_name": "com.example.middleware_app"
        }
      },
      "oauth_client": [
        {
          "client_id": "451569691926-ho65u1qdfv3hccffqbpr0pc4iuo3bhc7.apps.googleusercontent.com",
          "client_type": 3
        }
      ],
      "api_key": [
        {
          "current_key": "AIzaSyD2KnyQGHNSPbH04mpIIX-wD99A3A-qHQU"
        }
      ],
      "services": {
        "appinvite_service": {
          "other_platform_oauth_client": [
            {
              "client_id": "451569691926-ho65u1qdfv3hccffqbpr0pc4iuo3bhc7.apps.googleusercontent.com",
              "client_type": 3
            }
          ]
        }
      }
    }
  ],
  "configuration_version": "1"
}